deepmem/__init__.py
deepmem/_main.py
deepmem/_version.py
deepmem/data.py
deepmem/model.py
deepmem/networks.py
deepmem/options.py
deepmem/utils.py
deepmem-0.0.1.dist-info/LICENSE
deepmem-0.0.1.dist-info/METADATA
deepmem-0.0.1.dist-info/WHEEL
deepmem-0.0.1.dist-info/entry_points.txt
deepmem-0.0.1.dist-info/top_level.txt
deepmem-0.0.1.dist-info/RECORD
