Metadata-Version: 2.1
Name: deepmem
Version: 0.0.1
Summary: Deep learning implementations for sustainable matrix element method calculations
Home-page: https://github.com/mihirkatare/DeepMEM
Author: Mihir Katare
Author-email: mkatare2@illinois.edu
License: Apache
Project-URL: Source, https://github.com/mihirkatare/DeepMEM
Project-URL: Tracker, https://github.com/mihirkatare/DeepMEM/issues
Keywords: physics mem "deep learning"
Platform: UNKNOWN
Classifier: Development Status :: 3 - Alpha
Classifier: License :: OSI Approved :: Apache Software License
Classifier: Intended Audience :: Science/Research
Classifier: Topic :: Scientific/Engineering
Classifier: Topic :: Scientific/Engineering :: Physics
Classifier: Programming Language :: Python :: 3
Classifier: Programming Language :: Python :: 3.7
Classifier: Programming Language :: Python :: 3.8
Classifier: Programming Language :: Python :: 3.9
Classifier: Programming Language :: Python :: Implementation :: CPython
Requires-Python: >=3.7
License-File: LICENSE
Requires-Dist: awkward (>=1.3.0)
Requires-Dist: hist[plot] (>=2.4.0)
Requires-Dist: matplotlib (>=3.4)
Requires-Dist: scikit-learn (~=0.24)
Requires-Dist: torchvision (>=0.9.1)
Requires-Dist: uproot (>=4.0.9)
Provides-Extra: all
Requires-Dist: black[jupyter] ; extra == 'all'
Requires-Dist: flake8 ; extra == 'all'
Provides-Extra: lint
Requires-Dist: black[jupyter] ; extra == 'lint'
Requires-Dist: flake8 ; extra == 'lint'
